odoo8_addon_l10n_br_data_account_service-8.0.1.0.0.99.dev4-py2.7-nspkg.pth
odoo_addons/l10n_br_data_account_service/__openerp__.py
odoo_addons/l10n_br_data_account_service/__init__.py
odoo_addons/l10n_br_data_account_service/README.rst
odoo_addons/l10n_br_data_account_service/i18n/pt_BR.po
odoo_addons/l10n_br_data_account_service/data/account_fiscal_position_rule_data.xml
odoo_addons/l10n_br_data_account_service/data/l10n_br_data_account_service_data.xml
odoo_addons/l10n_br_data_account_service/demo/l10n_br_data_account_service_demo.xml
odoo_addons/l10n_br_data_account_service/static/description/icon.png
odoo8_addon_l10n_br_data_account_service-8.0.1.0.0.99.dev4.dist-info/top_level.txt
odoo8_addon_l10n_br_data_account_service-8.0.1.0.0.99.dev4.dist-info/WHEEL
odoo8_addon_l10n_br_data_account_service-8.0.1.0.0.99.dev4.dist-info/RECORD
odoo8_addon_l10n_br_data_account_service-8.0.1.0.0.99.dev4.dist-info/metadata.json
odoo8_addon_l10n_br_data_account_service-8.0.1.0.0.99.dev4.dist-info/DESCRIPTION.rst
odoo8_addon_l10n_br_data_account_service-8.0.1.0.0.99.dev4.dist-info/METADATA
odoo8_addon_l10n_br_data_account_service-8.0.1.0.0.99.dev4.dist-info/namespace_packages.txt
